object_tracker/__init__.py
object_tracker/changelog.py
object_tracker/exceptions.py
object_tracker/tracker.py
object_tracker/types.py
object_tracker-2.0.0.dist-info/LICENSE
object_tracker-2.0.0.dist-info/METADATA
object_tracker-2.0.0.dist-info/WHEEL
object_tracker-2.0.0.dist-info/top_level.txt
object_tracker-2.0.0.dist-info/RECORD
