Metadata-Version: 2.1
Name: object-tracker
Version: 2.0.0
Summary: A pure python object change and history tracker. Monitor all changes in your objects lifecycle and trigger callback functions to capture them.
Home-page: https://github.com/saurabh0719/object-tracker
Author: Saurabh Pujari
Author-email: saurabhpuj99@gmail.com
License: three-clause BSD
Project-URL: Documentation, https://github.com/saurabh0719/object-tracker#README
Project-URL: Source, https://github.com/saurabh0719/object-tracker
Keywords: object_tracker,object-tracker,changelog,object history,tracker,change tracker,history,state,state tracker
Classifier: Development Status :: 5 - Production/Stable
Classifier: Intended Audience :: Developers
Classifier: License :: OSI Approved :: BSD License
Classifier: Programming Language :: Python
License-File: LICENSE
